README.rst
setup.py
iac/__init__.py
iac/interfaces.py
iac/interpreter.py
iac/modify_interfaces.py
iac/parser.py
iac/parsetab.py
iac/server.py
iac/app/__init__.py
iac/app/gnumeric.py
iac/app/libreoffice/__init__.py
iac/app/libreoffice/calc.py
iac/app/libreoffice/writer.py
iac_protocol.egg-info/PKG-INFO
iac_protocol.egg-info/SOURCES.txt
iac_protocol.egg-info/dependency_links.txt
iac_protocol.egg-info/entry_points.txt
iac_protocol.egg-info/top_level.txt