Metadata-Version: 1.1
Name: iac-protocol
Version: 0.301
Summary: An interface/protocol that provides inter-application communication and scripting.
Home-page: https://github.com/Risto-Stevcev/iac-protocol
Author: Risto Stevcev
Author-email: risto1@gmail.com
License: BSD
Platform: UNKNOWN
Classifier: Development Status :: 4 - Beta
Classifier: Environment :: Console
Classifier: Intended Audience :: Developers
Classifier: Intended Audience :: End Users/Desktop
Classifier: Intended Audience :: Science/Research
Classifier: License :: OSI Approved :: BSD License
Classifier: Natural Language :: English
Classifier: Operating System :: OS Independent
Classifier: Programming Language :: Python :: 3
Classifier: Topic :: Home Automation
Classifier: Topic :: Scientific/Engineering
Classifier: Topic :: Scientific/Engineering :: Electronic Design Automation (EDA)
Classifier: Topic :: Scientific/Engineering :: Interface Engine/Protocol Translator
Classifier: Topic :: Software Development :: Interpreters
Classifier: Topic :: Software Development :: User Interfaces
Classifier: Topic :: Utilities
